Metadata-Version: 2.1
Name: motifscan
Version: 1.3.0
Summary: A package for motif discovery and motif enrichment analysis
Home-page: https://github.com/shao-lab/MotifScan
Author: Hayden Sun
Author-email: sunhongduo@picb.ac.cn
License: BSD
Project-URL: Bug Tracker, https://github.com/shao-lab/MotifScan/issues
Project-URL: Documentation, https://motifscan.readthedocs.io
Project-URL: Source Code, https://github.com/shao-lab/MotifScan
Platform: UNKNOWN
Classifier: Development Status :: 5 - Production/Stable
Classifier: Environment :: Console
Classifier: Intended Audience :: Science/Research
Classifier: License :: OSI Approved :: BSD License
Classifier: Operating System :: Unix
Classifier: Operating System :: POSIX
Classifier: Operating System :: MacOS
Classifier: Programming Language :: Python
Classifier: Programming Language :: Python :: 3
Classifier: Programming Language :: Python :: 3.6
Classifier: Programming Language :: Python :: 3.7
Classifier: Programming Language :: Python :: 3.8
Classifier: Topic :: Scientific/Engineering :: Bio-Informatics
Requires-Python: >=3.6
Provides-Extra: test
Provides-Extra: docs
